src/marvin/__init__.py
src/marvin/spytools/default_config.ini
src/marvin/spytools/spio.py
spytools-0.0.8.post6.dist-info/LICENSE.md
spytools-0.0.8.post6.dist-info/METADATA
spytools-0.0.8.post6.dist-info/WHEEL
spytools-0.0.8.post6.dist-info/RECORD
