Metadata-Version: 2.1
Name: SPyTools
Version: 0.0.8.post6
Summary: Magical Marvin SharePoint Tools in Python
Author: Roeland Maes
Author-email: roeland.maes@vito.be
Requires-Python: >=3.10,<4.0
Classifier: Programming Language :: Python :: 3
Classifier: Programming Language :: Python :: 3.10
Classifier: Programming Language :: Python :: 3.11
Classifier: Programming Language :: Python :: 3.12
Provides-Extra: full
Provides-Extra: pandas
Provides-Extra: pandas-parquet
Provides-Extra: pandas-xlsx
Requires-Dist: Office365-REST-Python-Client (>=2.3,<3.0)
Requires-Dist: cfgrib (>=0.9,<0.10) ; extra == "full"
Requires-Dist: dynaconf (>=3.1,<4.0) ; extra == "full"
Requires-Dist: fiona (>=1.9,<2.0) ; extra == "full"
Requires-Dist: geopandas (>=0.14,<0.15) ; extra == "full"
Requires-Dist: h5netcdf (>=1.0,<2.0) ; extra == "full"
Requires-Dist: matplotlib (>=3.8,<4.0) ; extra == "full"
Requires-Dist: msal_extensions (>=0.3,<0.4)
Requires-Dist: netcdf4 (>=1.6,<2.0) ; extra == "full"
Requires-Dist: numpy (>=1.25,<2.0) ; extra == "full"
Requires-Dist: openpyxl (>=3.1,<4.0) ; extra == "full"
Requires-Dist: pandas (>=1.5,<2.0) ; extra == "pandas" or extra == "pandas-xlsx" or extra == "pandas-parquet" or extra == "full"
Requires-Dist: pyarrow (>=13.0,<14.0) ; extra == "pandas-parquet" or extra == "full"
Requires-Dist: pyexcelerate (>=0.6,<0.7) ; extra == "full"
Requires-Dist: pyproj (>=3.6,<4.0) ; extra == "full"
Requires-Dist: rasterio (>=1.3,<2.0) ; extra == "full"
Requires-Dist: xlsxwriter (>=3.1,<4.0) ; extra == "pandas-xlsx" or extra == "full"
